vap/__init__.py
vap/cli.py
vap/errors.py
vap/verifier.py
vap-1.1.0.dist-info/LICENSE
vap-1.1.0.dist-info/METADATA
vap-1.1.0.dist-info/WHEEL
vap-1.1.0.dist-info/entry_points.txt
vap-1.1.0.dist-info/top_level.txt
vap-1.1.0.dist-info/RECORD
